notes.py
secrets.py
secret_notes-0.1.dist-info/entry_points.txt
secret_notes-0.1.dist-info/RECORD
secret_notes-0.1.dist-info/WHEEL
secret_notes-0.1.dist-info/metadata.json
secret_notes-0.1.dist-info/METADATA
secret_notes-0.1.dist-info/DESCRIPTION.rst
secret_notes-0.1.dist-info/top_level.txt
