Metadata-Version: 2.0
Name: secret-notes
Version: 0.1
Summary: store your secrets using GPG!
Home-page: https://github.com/aliceriot/secrets
Author: Alice Pote
Author-email: alice.writes.wrongs@gmail.com
License: GPLv3
Platform: UNKNOWN
Requires-Dist: python-gnupg
